hssm/__init__.py
hssm/_types.py
hssm/config.py
hssm/data_validator.py
hssm/datasets.py
hssm/defaults.py
hssm/hssm.py
hssm/link.py
hssm/prior.py
hssm/register.py
hssm/simulator.py
hssm/utils.py
hssm/datasets/cavanagh_theta_nn.csv
hssm/datasets/cavanagh_theta_nn_old.csv
hssm/distribution_utils/__init__.py
hssm/distribution_utils/blackbox.py
hssm/distribution_utils/dist.py
hssm/distribution_utils/func_utils.py
hssm/distribution_utils/jax.py
hssm/distribution_utils/onnx.py
hssm/distribution_utils/onnx_utils/__init__.py
hssm/distribution_utils/onnx_utils/model.py
hssm/distribution_utils/onnx_utils/onnx2jax.py
hssm/distribution_utils/onnx_utils/onnx2pt.py
hssm/distribution_utils/onnx_utils/onnx2xla.py
hssm/likelihoods/__init__.py
hssm/likelihoods/analytical.py
hssm/likelihoods/blackbox.py
hssm/likelihoods/rldm.py
hssm/likelihoods/rldm_optimized.py
hssm/modelconfig/__init__.py
hssm/modelconfig/angle_config.py
hssm/modelconfig/ddm_config.py
hssm/modelconfig/ddm_sdv_config.py
hssm/modelconfig/ddm_seq2_no_bias_config.py
hssm/modelconfig/full_ddm_config.py
hssm/modelconfig/lba2_config.py
hssm/modelconfig/lba3_config.py
hssm/modelconfig/levy_config.py
hssm/modelconfig/ornstein_config.py
hssm/modelconfig/race_no_bias_angle_4_config.py
hssm/modelconfig/weibull_config.py
hssm/param/__init__.py
hssm/param/param.py
hssm/param/params.py
hssm/param/regression_param.py
hssm/param/simple_param.py
hssm/param/user_param.py
hssm/param/utils.py
hssm/plotting/__init__.py
hssm/plotting/model_cartoon.py
hssm/plotting/predictive.py
hssm/plotting/quantile_probability.py
hssm/plotting/utils.py
hssm-0.2.11.dist-info/METADATA
hssm-0.2.11.dist-info/WHEEL
hssm-0.2.11.dist-info/licenses/LICENSE
hssm-0.2.11.dist-info/RECORD
