Metadata-Version: 2.4
Name: HSSM
Version: 0.2.11
Summary: Bayesian inference for hierarchical sequential sampling models.
Project-URL: homepage, https://lnccbrown.github.io/HSSM/
Project-URL: documentation, https://lnccbrown.github.io/HSSM/
Project-URL: repository, https://github.com/lnccbrown/HSSM
Author-email: Alexander Fengler <alexander_fengler@brown.edu>, Paul Xu <yang_xu@brown.edu>, Carlos Paniagua <carlos_paniagua@brown.edu>, Krishn Bera <krishn_bera@brown.edu>, Aisulu Omar <aisulu_omar@brown.edu>, Michael Frank <michael_frank@brown.edu>
License: Copyright 2023, Brown University, Providence, RI.
License-File: LICENSE
Keywords: HSSM,bayes,bayesian,mcmc,sequential sampling models
Classifier: Programming Language :: Python :: 3
Classifier: Programming Language :: Python :: 3 :: Only
Classifier: Programming Language :: Python :: 3.11
Classifier: Programming Language :: Python :: 3.12
Requires-Python: <3.13,>=3.11
Requires-Dist: arviz>=0.22.0
Requires-Dist: bambi<0.16.0,>=0.15.0
Requires-Dist: cloudpickle>=3.0.0
Requires-Dist: hddm-wfpt>=0.1.5
Requires-Dist: huggingface-hub>=0.34.0
Requires-Dist: jaxonnxruntime>=0.3.0
Requires-Dist: numpyro>=0.19
Requires-Dist: onnx>=1.16.0
Requires-Dist: pymc>=5.25.0
Requires-Dist: seaborn>=0.13.2
Requires-Dist: ssm-simulators>=0.11.3
Requires-Dist: tqdm>=4.66.0
Provides-Extra: cuda12
Requires-Dist: jax[cuda12]>=0.5.2; extra == 'cuda12'
